sklearn_ann/__init__.py
sklearn_ann/test_utils.py
sklearn_ann/utils.py
sklearn_ann/cluster/__init__.py
sklearn_ann/cluster/rnn_dbscan.py
sklearn_ann/kneighbors/__init__.py
sklearn_ann/kneighbors/annoy.py
sklearn_ann/kneighbors/faiss.py
sklearn_ann/kneighbors/nmslib.py
sklearn_ann/kneighbors/pynndescent.py
sklearn_ann/kneighbors/sklearn.py
sklearn_ann-0.1.4.dist-info/METADATA
sklearn_ann-0.1.4.dist-info/WHEEL
sklearn_ann-0.1.4.dist-info/licenses/LICENSE
sklearn_ann-0.1.4.dist-info/RECORD
