Metadata-Version: 2.4
Name: sklearn-ann
Version: 0.1.4
Summary: Various integrations for ANN (Approximate Nearest Neighbours) libraries into scikit-learn.
Project-URL: Source, https://github.com/scikit-learn-contrib/sklearn-ann
Project-URL: Documentation, https://sklearn-ann.readthedocs.io/
Author-email: Frankie Robertson <frankie@robertson.name>, Philipp Angerer <phil.angerer@gmail.com>
License-Expression: BSD-3-Clause
License-File: LICENSE
Requires-Python: >=3.9
Requires-Dist: scikit-learn>=1.6.0
Requires-Dist: scipy<2.0.0,>=1.11.1
Provides-Extra: annlibs
Requires-Dist: annoy<2.0.0,>=1.17.0; extra == 'annlibs'
Requires-Dist: faiss-cpu<2.0.0,>=1.6.5; extra == 'annlibs'
Requires-Dist: nmslib-metabrainz<3.0.0,>=2.1.1; extra == 'annlibs'
Requires-Dist: numba>=0.52; extra == 'annlibs'
Requires-Dist: pynndescent<1.0.0,>=0.5.1; extra == 'annlibs'
Provides-Extra: annoy
Requires-Dist: annoy<2.0.0,>=1.17.0; extra == 'annoy'
Provides-Extra: docs
Requires-Dist: matplotlib>=3.3.3; extra == 'docs'
Requires-Dist: numpydoc>=1.1.0; extra == 'docs'
Requires-Dist: scanpydoc; extra == 'docs'
Requires-Dist: sphinx-book-theme>=1.1.0; extra == 'docs'
Requires-Dist: sphinx-gallery>=0.8.2; extra == 'docs'
Requires-Dist: sphinx-issues>=1.2.0; extra == 'docs'
Requires-Dist: sphinx>=7; extra == 'docs'
Provides-Extra: faiss
Requires-Dist: faiss-cpu<2.0.0,>=1.6.5; extra == 'faiss'
Provides-Extra: nmslib
Requires-Dist: nmslib-metabrainz<3.0.0,>=2.1.1; extra == 'nmslib'
Provides-Extra: pynndescent
Requires-Dist: numba>=0.52; extra == 'pynndescent'
Requires-Dist: pynndescent<1.0.0,>=0.5.1; extra == 'pynndescent'
Provides-Extra: tests
Requires-Dist: pytest-cov>=2.10.1; extra == 'tests'
Requires-Dist: pytest>=6.2.1; extra == 'tests'
